Workbook

Sheet Sheet1
A1: Income Statement | G1: Balance Sheet | L1: Additional Data(for Ratios)
A2: Year | B2: Revenue | C2: Cost | D2: Operating Expenses | E2: Net Profit | G2: Year | H2: Total Assets | I2: Total Liabilities | J2: Equity | L2: Year | M2: Current Assets | N2: Current Liabilities
A3: 2019 | B3: 500000 | C3: 300000 | D3: 100000 | E3: 100000 | G3: 2019 | H3: 800000 | I3: 400000 | J3: 400000 | L3: 2019 | M3: 300000 | N3: 150000
A4: 2020 | B4: 600000 | C4: 350000 | D4: 120000 | E4: 130000 | G4: 2020 | H4: 900000 | I4: 450000 | J4: 450000 | L4: 2020 | M4: 350000 | N4: 180000
A5: 2021 | B5: 750000 | C5: 400000 | D5: 150000 | E5: 200000 | G5: 2021 | H5: 1100000 | I5: 500000 | J5: 600000 | L5: 2021 | M5: 400000 | N5: 200000
A6: 2022 | B6: 900000 | C6: 500000 | D6: 180000 | E6: 220000 | G6: 2022 | H6: 1300000 | I6: 600000 | J6: 700000 | L6: 2022 | M6: 450000 | N6: 250000
A7: 2023 | B7: 1100000 | C7: 600000 | D7: 200000 | E7: 300000 | G7: 2023 | H7: 1500000 | I7: 700000 | J7: 800000 | L7: 2023 | M7: 500000 | N7: 300000
A10: Year | B10: profit margin | C10: Revenue Growth | D10: Current Ratio | E10: DEBT-TO-EQUITY RATIO
A11: 2020 | B11: {=E3:E7/B3:B7} -> 0.2 | C11: =(B4-B3)/B3 -> 0.2 | D11: =(M3/N3) -> 2 | E11: =I3/J3 -> 1
A12: 2021 | B12: 0.21666667 | C12: =(B5-B4)/B4 -> 0.25 | D12: =(M4/N4) -> 1.9444444 | E12: =I4/J4 -> 1
A13: 2022 | B13: 0.26666667 | C13: =(B6-B5)/B5 -> 0.2 | D13: =(M5/N5) -> 2 | E13: =I5/J5 -> 0.83333333
A14: 2023 | B14: 0.24444444 | C14: =(B7-B6)/B6 -> 0.22222222 | D14: =(M6/N6) -> 1.8 | E14: =I6/J6 -> 0.85714286
A15: 2024 | B15: 0.27272727 | C15: =(B8-B7)/B7 -> -1 | D15: =(M7/N7) -> 1.6666667 | E15: =I7/J7 -> 0.875

Sheet Financial Performance Dashboard
A1: Financial Performance Dashboard (2019–2023)
A2: Year | B2: Total Revenue | C2: =Sheet1!E2 -> Net Profit | D2: =Sheet1!B10 -> profit margin | E2: Year | F2: =Sheet1!C10 -> Revenue Growth | I2: Total Revenue | J2: 1100000 | L2: Insights
A3: 2019 | B3: 500000 | C3: =Sheet1!E3 -> 100000 | D3: =Sheet1!B11 -> 0.2 | E3: 2020 | F3: =Sheet1!C11 -> 0.2 | I3: Net Profit | J3: 300000 | L3: Revenue increased steadily from 5L to 11L (strong growth) Profit margin improved to 27% in 2023 Growth rate peaked at 25% in 2021 Company shows stable financial performance
A4: 2020 | B4: 600000 | C4: =Sheet1!E4 -> 130000 | D4: =Sheet1!B12 -> 0.21666667 | E4: 2021 | F4: =Sheet1!C12 -> 0.25 | I4: Profit Margin | J4: 0.27
A5: 2021 | B5: 750000 | C5: =Sheet1!E5 -> 200000 | D5: =Sheet1!B13 -> 0.26666667 | E5: 2022 | F5: =Sheet1!C13 -> 0.2 | I5: Growth | J5: 0.22
A6: 2022 | B6: 900000 | C6: =Sheet1!E6 -> 220000 | D6: =Sheet1!B14 -> 0.24444444 | E6: 2023 | F6: =Sheet1!C14 -> 0.22222222 | I6: Current Ratio | J6: 0.0167
A7: 2023 | B7: 1100000 | C7: =Sheet1!E7 -> 300000 | D7: =Sheet1!B15 -> 0.27272727 | E7: 2024
